xchg/__init__.py
xchg/common.py
xchg/download_candles.py
xchg/xchg.py
xchg-6.0.1.dist-info/LICENSE
xchg-6.0.1.dist-info/METADATA
xchg-6.0.1.dist-info/WHEEL
xchg-6.0.1.dist-info/entry_points.txt
xchg-6.0.1.dist-info/top_level.txt
xchg-6.0.1.dist-info/RECORD
