Metadata-Version: 2.1
Name: xchg
Version: 6.0.1
Summary: Simulator of a currency exchange.
Home-page: https://github.com/sergei-bondarenko/xchg
Author: Sergei Bondarenko
Author-email: sergei@bondarenko.xyz
License: Unlicense
Platform: UNKNOWN
Classifier: Development Status :: 5 - Production/Stable
Classifier: Programming Language :: Python :: 3
Classifier: Programming Language :: Python :: 3.6
Classifier: Programming Language :: Python :: 3.7
Classifier: Programming Language :: Python :: 3.8
Requires-Dist: pandas
Requires-Dist: poloniex
Requires-Dist: numpy
